<?xml version="1.0"?>
<testResults>
  <FitNesseVersion>v20190224</FitNesseVersion>
  <rootPath>JerreWebPage.JerreWebPageSuite.SuiteSetUp</rootPath>
  <result>
    <counts>
      <right>0</right>
      <wrong>0</wrong>
      <ignores>0</ignores>
      <exceptions>0</exceptions>
    </counts>
    <date>2019-07-07T20:30:09+02:00</date>
    <runTimeInMillis>118</runTimeInMillis>
    <content>&lt;br/&gt;&lt;div class="contents"&gt;
	&lt;b&gt;Contents:&lt;/b&gt;
	&lt;ul class="toc1"/&gt;&lt;ul class="toc1"/&gt;
&lt;/div&gt;
&lt;br/&gt;</content>
    <relativePageName>SuiteSetUp</relativePageName>
  </result>
  <finalCounts>
    <right>1</right>
    <wrong>0</wrong>
    <ignores>0</ignores>
    <exceptions>0</exceptions>
  </finalCounts>
  <totalRunTimeInMillis>118</totalRunTimeInMillis>
</testResults>

